pulumi_astronomer
