Metadata-Version: 2.1
Name: pulumi-astronomer
Version: 0.2.8
Summary: A Pulumi package for creating and managing Astronomer Cloud resources
Home-page: https://github.com/ryan-pip/pulumi-astronomer
License: Apache-2.0
Project-URL: Repository, https://github.com/ryan-pip/pulumi-astronomer
Keywords: pulumi astronomer category/infrastructure
Platform: UNKNOWN
Requires-Python: >=3.9
